{"links": {"self": {"href": "data/repositories/osrf/gazebo_tutorials/pullrequests/200/comments/5940480.json"}, "code": {"href": "https://api.bitbucket.org/2.0/repositories/osrf/gazebo_tutorials/diff/osrf/gazebo_tutorials:06f52c1f781f..1f9391c953c0?path=drcsim_atlas_robot_interface%2Ftutorial.md"}, "html": {"href": "#!/osrf/gazebo_tutorials/pull-requests/200/_/diff#comment-5940480"}}, "deleted": false, "pullrequest": {"type": "pullrequest", "id": 200, "links": {"self": {"href": "data/repositories/osrf/gazebo_tutorials/pullrequests/200.json"}, "html": {"href": "#!/osrf/gazebo_tutorials/pull-requests/200"}}, "title": "issue #24, AtlasRobotInterface Tutorial for updated v3.0.0"}, "content": {"raw": "I prefer removing the backticks around `src/atlas_interface.cpp` so it actually looks like a link", "markup": "markdown", "html": "<p>I prefer removing the backticks around <code>src/atlas_interface.cpp</code> so it actually looks like a link</p>", "type": "rendered"}, "created_on": "2015-03-28T01:04:03.925955+00:00", "user": {"display_name": "Steve Peters", "uuid": "{2ccfed09-18b8-4921-8d58-15ef01092802}", "links": {"self": {"href": "https://api.bitbucket.org/2.0/users/%7B2ccfed09-18b8-4921-8d58-15ef01092802%7D"}, "html": {"href": "https://bitbucket.org/%7B2ccfed09-18b8-4921-8d58-15ef01092802%7D/"}, "avatar": {"href": "data/secure.gravatar.com/avatar/1fb4816dad9e68337d3096f750951f6cd=httpsavatar-management--avatars.us-west-2.prod.public.atl-paas.netinitialsSP-1.png"}}, "nickname": "Steven Peters", "type": "user", "account_id": "557058:5de38267-b118-494c-aa76-4fab35448816"}, "inline": {"to": 32, "from": null, "outdated": true, "path": "drcsim_atlas_robot_interface/tutorial.md"}, "updated_on": "2015-03-28T01:04:03.933123+00:00", "type": "pullrequest_comment", "id": 5940480}