{"links": {"self": {"href": "data/repositories/osrf/gazebo_tutorials/pullrequests/410/comments/30270297.json"}, "code": {"href": "https://api.bitbucket.org/2.0/repositories/osrf/gazebo_tutorials/diff/osrf/gazebo_tutorials:5fb4692d71ad..bb26d88a153c?path=attach_gripper%2Ffiles%2Fmodel-1.9%2B.config"}, "html": {"href": "#!/osrf/gazebo_tutorials/pull-requests/410/_/diff#comment-30270297"}}, "deleted": false, "pullrequest": {"type": "pullrequest", "id": 410, "links": {"self": {"href": "data/repositories/osrf/gazebo_tutorials/pullrequests/410.json"}, "html": {"href": "#!/osrf/gazebo_tutorials/pull-requests/410"}}, "title": "Split tutorial into 1.9+ and 6+ versions"}, "content": {"raw": "humm I wonder if it matters whether this version matches the one on the SDF file", "markup": "markdown", "html": "<p>humm I wonder if it matters whether this version matches the one on the SDF file</p>", "type": "rendered"}, "created_on": "2017-01-24T21:53:05.121128+00:00", "user": {"display_name": "Louise Poubel", "uuid": "{5cfa2075-477b-4ded-bdb9-8d2479544ec4}", "links": {"self": {"href": "https://api.bitbucket.org/2.0/users/%7B5cfa2075-477b-4ded-bdb9-8d2479544ec4%7D"}, "html": {"href": "https://bitbucket.org/%7B5cfa2075-477b-4ded-bdb9-8d2479544ec4%7D/"}, "avatar": {"href": "https://avatar-management--avatars.us-west-2.prod.public.atl-paas.net/557058:6ff86fcb-b7ab-44a5-b8a6-f6d9cae8b6e8/7d903d90-c5ea-4182-b7ef-0d467e9e1c74/128"}}, "nickname": "chapulina", "type": "user", "account_id": "557058:6ff86fcb-b7ab-44a5-b8a6-f6d9cae8b6e8"}, "inline": {"to": 5, "from": null, "outdated": false, "path": "attach_gripper/files/model-1.9+.config"}, "updated_on": "2017-01-24T21:53:05.124515+00:00", "type": "pullrequest_comment", "id": 30270297}