{"links": {"self": {"href": "data/repositories/osrf/gazebo_tutorials/pullrequests/436/comments/43346476.json"}, "code": {"href": "https://api.bitbucket.org/2.0/repositories/osrf/gazebo_tutorials/diff/pchorak/gazebo_tutorials:962ed52b4dbd..2650dac76ff4?path=gravity_compensation%2Ftutorial.md"}, "html": {"href": "#!/osrf/gazebo_tutorials/pull-requests/436/_/diff#comment-43346476"}}, "deleted": false, "pullrequest": {"type": "pullrequest", "id": 436, "links": {"self": {"href": "data/repositories/osrf/gazebo_tutorials/pullrequests/436.json"}, "html": {"href": "#!/osrf/gazebo_tutorials/pull-requests/436"}}, "title": "Gravity compensation plugin tutorial"}, "content": {"raw": "If the mass is of 0.1kg, I would prefer state at the very beginning: \"we have a Mass on rail model with a cube of mass 0,1kg\" Such  that users would have already known this at the P control section ", "markup": "markdown", "html": "<p>If the mass is of 0.1kg, I would prefer state at the very beginning: \"we have a Mass on rail model with a cube of mass 0,1kg\" Such  that users would have already known this at the P control section </p>", "type": "rendered"}, "created_on": "2017-08-22T22:58:20.795135+00:00", "user": {"display_name": "Ying Lu", "uuid": "{11ec131e-4af6-4228-beaf-167b1c8d1c2c}", "links": {"self": {"href": "https://api.bitbucket.org/2.0/users/%7B11ec131e-4af6-4228-beaf-167b1c8d1c2c%7D"}, "html": {"href": "https://bitbucket.org/%7B11ec131e-4af6-4228-beaf-167b1c8d1c2c%7D/"}, "avatar": {"href": "https://avatar-management--avatars.us-west-2.prod.public.atl-paas.net/557058:659bfe31-d941-44f5-aa6d-00058b070ea8/c88d5925-8a09-40c7-8684-c02aeafe0f59/128"}}, "nickname": "rosebudflyaway", "type": "user", "account_id": "557058:659bfe31-d941-44f5-aa6d-00058b070ea8"}, "inline": {"to": 66, "from": null, "outdated": true, "path": "gravity_compensation/tutorial.md"}, "updated_on": "2017-08-22T22:58:20.797288+00:00", "type": "pullrequest_comment", "id": 43346476}