{"pagelen": 50, "values": [{"update": {"description": "Redo of pull request #265.\r\n\r\n**Note**: The `wget` links are set to URL values that will exist after [this pull-request](https://bitbucket.org/osrf/gazebo/pull-requests/1941) is merged.\r\n\r\nhttp://gazebosim.org/tutorials?tut=wide_angle_camera&branch=wideangle", "title": "Wide angle camera tutorial", "destination": {"commit": {"hash": "1381e2fb3df1", "type": "commit", "links": {"self": {"href": "data/repositories/osrf/gazebo_tutorials/commit/1381e2fb3df1.json"}, "html": {"href": "#!/osrf/gazebo_tutorials/commits/1381e2fb3df1"}}}, "repository": {"links": {"self": {"href": "data/repositories/osrf/gazebo_tutorials.json"}, "html": {"href": "#!/osrf/gazebo_tutorials"}, "avatar": {"href": "data/bytebucket.org/ravatar/{9adb672c-d31a-4c2b-bae4-8d5870291649}ts=1736722"}}, "type": "repository", "name": "gazebo_tutorials", "full_name": "osrf/gazebo_tutorials", "uuid": "{9adb672c-d31a-4c2b-bae4-8d5870291649}"}, "branch": {"name": "default"}}, "reason": "Wide angle camera is broken", "source": {"commit": {"hash": "981e45aa54b9", "type": "commit", "links": {"self": {"href": "data/repositories/osrf/gazebo_tutorials/commit/981e45aa54b9.json"}, "html": {"href": "#!/osrf/gazebo_tutorials/commits/981e45aa54b9"}}}, "repository": {"links": {"self": {"href": "data/repositories/osrf/gazebo_tutorials.json"}, "html": {"href": "#!/osrf/gazebo_tutorials"}, "avatar": {"href": "data/bytebucket.org/ravatar/{9adb672c-d31a-4c2b-bae4-8d5870291649}ts=1736722"}}, "type": "repository", "name": "gazebo_tutorials", "full_name": "osrf/gazebo_tutorials", "uuid": "{9adb672c-d31a-4c2b-bae4-8d5870291649}"}, "branch": {"name": "wideangle"}}, "state": "DECLINED", "author": {"display_name": "Nate Koenig", "uuid": "{c862cdd9-fcc8-4419-9fc7-e20db14b8fcb}", "links": {"self": {"href": "https://api.bitbucket.org/2.0/users/%7Bc862cdd9-fcc8-4419-9fc7-e20db14b8fcb%7D"}, "html": {"href": "https://bitbucket.org/%7Bc862cdd9-fcc8-4419-9fc7-e20db14b8fcb%7D/"}, "avatar": {"href": "https://avatar-management--avatars.us-west-2.prod.public.atl-paas.net/557058:095b1e12-74ed-4e20-b44f-2f0745b616e0/ca24bb11-4787-4b14-a20d-d91835e9bde2/128"}}, "nickname": "Nathan Koenig", "type": "user", "account_id": "557058:095b1e12-74ed-4e20-b44f-2f0745b616e0"}, "date": "2015-11-10T23:08:22.512614+00:00"}, "pull_request": {"type": "pullrequest", "id": 277, "links": {"self": {"href": "data/repositories/osrf/gazebo_tutorials/pullrequests/277.json"}, "html": {"href": "#!/osrf/gazebo_tutorials/pull-requests/277"}}, "title": "Wide angle camera tutorial"}}, {"update": {"description": "Redo of pull request #265.\r\n\r\n**Note**: The `wget` links are set to URL values that will exist after [this pull-request](https://bitbucket.org/osrf/gazebo/pull-requests/1941) is merged.\r\n\r\nhttp://gazebosim.org/tutorials?tut=wide_angle_camera&branch=wideangle", "title": "Wide angle camera tutorial", "destination": {"commit": {"hash": "1381e2fb3df1", "type": "commit", "links": {"self": {"href": "data/repositories/osrf/gazebo_tutorials/commit/1381e2fb3df1.json"}, "html": {"href": "#!/osrf/gazebo_tutorials/commits/1381e2fb3df1"}}}, "repository": {"links": {"self": {"href": "data/repositories/osrf/gazebo_tutorials.json"}, "html": {"href": "#!/osrf/gazebo_tutorials"}, "avatar": {"href": "data/bytebucket.org/ravatar/{9adb672c-d31a-4c2b-bae4-8d5870291649}ts=1736722"}}, "type": "repository", "name": "gazebo_tutorials", "full_name": "osrf/gazebo_tutorials", "uuid": "{9adb672c-d31a-4c2b-bae4-8d5870291649}"}, "branch": {"name": "default"}}, "reason": "", "source": {"commit": {"hash": "981e45aa54b9", "type": "commit", "links": {"self": {"href": "data/repositories/osrf/gazebo_tutorials/commit/981e45aa54b9.json"}, "html": {"href": "#!/osrf/gazebo_tutorials/commits/981e45aa54b9"}}}, "repository": {"links": {"self": {"href": "data/repositories/osrf/gazebo_tutorials.json"}, "html": {"href": "#!/osrf/gazebo_tutorials"}, "avatar": {"href": "data/bytebucket.org/ravatar/{9adb672c-d31a-4c2b-bae4-8d5870291649}ts=1736722"}}, "type": "repository", "name": "gazebo_tutorials", "full_name": "osrf/gazebo_tutorials", "uuid": "{9adb672c-d31a-4c2b-bae4-8d5870291649}"}, "branch": {"name": "wideangle"}}, "state": "OPEN", "author": {"display_name": "Carlos Ag\u00fcero", "uuid": "{da8a8e89-4bb0-421b-bd0e-dbbed3d4ed6a}", "links": {"self": {"href": "https://api.bitbucket.org/2.0/users/%7Bda8a8e89-4bb0-421b-bd0e-dbbed3d4ed6a%7D"}, "html": {"href": "https://bitbucket.org/%7Bda8a8e89-4bb0-421b-bd0e-dbbed3d4ed6a%7D/"}, "avatar": {"href": "data/secure.gravatar.com/avatar/692bf15758111acaddae4da15a47f9e5d=httpsavatar-management--avatars.us-west-2.prod.public.atl-paas.netinitialsCA-0.png"}}, "nickname": "caguero", "type": "user", "account_id": "557058:4ded1ddf-947e-4154-bbd1-3dba24f1bdbd"}, "date": "2015-11-10T00:56:52.635186+00:00"}, "pull_request": {"type": "pullrequest", "id": 277, "links": {"self": {"href": "data/repositories/osrf/gazebo_tutorials/pullrequests/277.json"}, "html": {"href": "#!/osrf/gazebo_tutorials/pull-requests/277"}}, "title": "Wide angle camera tutorial"}}, {"update": {"description": "Redo of pull request #265.\r\n\r\n**Note**: The `wget` links are set to URL values that will exist after [this pull-request](https://bitbucket.org/osrf/gazebo/pull-requests/1941) is merged.\r\n\r\nhttp://gazebosim.org/tutorials?tut=wide_angle_camera&branch=wideangle", "title": "Wide angle camera tutorial", "destination": {"commit": {"hash": "1381e2fb3df1", "type": "commit", "links": {"self": {"href": "data/repositories/osrf/gazebo_tutorials/commit/1381e2fb3df1.json"}, "html": {"href": "#!/osrf/gazebo_tutorials/commits/1381e2fb3df1"}}}, "repository": {"links": {"self": {"href": "data/repositories/osrf/gazebo_tutorials.json"}, "html": {"href": "#!/osrf/gazebo_tutorials"}, "avatar": {"href": "data/bytebucket.org/ravatar/{9adb672c-d31a-4c2b-bae4-8d5870291649}ts=1736722"}}, "type": "repository", "name": "gazebo_tutorials", "full_name": "osrf/gazebo_tutorials", "uuid": "{9adb672c-d31a-4c2b-bae4-8d5870291649}"}, "branch": {"name": "default"}}, "reason": "", "source": {"commit": {"hash": "981e45aa54b9", "type": "commit", "links": {"self": {"href": "data/repositories/osrf/gazebo_tutorials/commit/981e45aa54b9.json"}, "html": {"href": "#!/osrf/gazebo_tutorials/commits/981e45aa54b9"}}}, "repository": {"links": {"self": {"href": "data/repositories/osrf/gazebo_tutorials.json"}, "html": {"href": "#!/osrf/gazebo_tutorials"}, "avatar": {"href": "data/bytebucket.org/ravatar/{9adb672c-d31a-4c2b-bae4-8d5870291649}ts=1736722"}}, "type": "repository", "name": "gazebo_tutorials", "full_name": "osrf/gazebo_tutorials", "uuid": "{9adb672c-d31a-4c2b-bae4-8d5870291649}"}, "branch": {"name": "wideangle"}}, "state": "OPEN", "author": {"display_name": "Carlos Ag\u00fcero", "uuid": "{da8a8e89-4bb0-421b-bd0e-dbbed3d4ed6a}", "links": {"self": {"href": "https://api.bitbucket.org/2.0/users/%7Bda8a8e89-4bb0-421b-bd0e-dbbed3d4ed6a%7D"}, "html": {"href": "https://bitbucket.org/%7Bda8a8e89-4bb0-421b-bd0e-dbbed3d4ed6a%7D/"}, "avatar": {"href": "data/secure.gravatar.com/avatar/692bf15758111acaddae4da15a47f9e5d=httpsavatar-management--avatars.us-west-2.prod.public.atl-paas.netinitialsCA-0.png"}}, "nickname": "caguero", "type": "user", "account_id": "557058:4ded1ddf-947e-4154-bbd1-3dba24f1bdbd"}, "date": "2015-11-10T00:56:48.939987+00:00"}, "pull_request": {"type": "pullrequest", "id": 277, "links": {"self": {"href": "data/repositories/osrf/gazebo_tutorials/pullrequests/277.json"}, "html": {"href": "#!/osrf/gazebo_tutorials/pull-requests/277"}}, "title": "Wide angle camera tutorial"}}, {"update": {"description": "Redo of pull request #265.\r\n\r\n**Note**: The `wget` links are set to URL values that will exist after [this pull-request](https://bitbucket.org/osrf/gazebo/pull-requests/1941) is merged.\r\n\r\nhttp://gazebosim.org/tutorials?tut=wide_angle_camera&branch=wideangle", "title": "Wide angle camera tutorial", "destination": {"commit": {"hash": "1381e2fb3df1", "type": "commit", "links": {"self": {"href": "data/repositories/osrf/gazebo_tutorials/commit/1381e2fb3df1.json"}, "html": {"href": "#!/osrf/gazebo_tutorials/commits/1381e2fb3df1"}}}, "repository": {"links": {"self": {"href": "data/repositories/osrf/gazebo_tutorials.json"}, "html": {"href": "#!/osrf/gazebo_tutorials"}, "avatar": {"href": "data/bytebucket.org/ravatar/{9adb672c-d31a-4c2b-bae4-8d5870291649}ts=1736722"}}, "type": "repository", "name": "gazebo_tutorials", "full_name": "osrf/gazebo_tutorials", "uuid": "{9adb672c-d31a-4c2b-bae4-8d5870291649}"}, "branch": {"name": "default"}}, "reason": "", "source": {"commit": {"hash": "b1cb559a8fbe", "type": "commit", "links": {"self": {"href": "data/repositories/osrf/gazebo_tutorials/commit/b1cb559a8fbe.json"}, "html": {"href": "#!/osrf/gazebo_tutorials/commits/b1cb559a8fbe"}}}, "repository": {"links": {"self": {"href": "data/repositories/osrf/gazebo_tutorials.json"}, "html": {"href": "#!/osrf/gazebo_tutorials"}, "avatar": {"href": "data/bytebucket.org/ravatar/{9adb672c-d31a-4c2b-bae4-8d5870291649}ts=1736722"}}, "type": "repository", "name": "gazebo_tutorials", "full_name": "osrf/gazebo_tutorials", "uuid": "{9adb672c-d31a-4c2b-bae4-8d5870291649}"}, "branch": {"name": "wideangle"}}, "state": "OPEN", "author": {"display_name": "Carlos Ag\u00fcero", "uuid": "{da8a8e89-4bb0-421b-bd0e-dbbed3d4ed6a}", "links": {"self": {"href": "https://api.bitbucket.org/2.0/users/%7Bda8a8e89-4bb0-421b-bd0e-dbbed3d4ed6a%7D"}, "html": {"href": "https://bitbucket.org/%7Bda8a8e89-4bb0-421b-bd0e-dbbed3d4ed6a%7D/"}, "avatar": {"href": "data/secure.gravatar.com/avatar/692bf15758111acaddae4da15a47f9e5d=httpsavatar-management--avatars.us-west-2.prod.public.atl-paas.netinitialsCA-0.png"}}, "nickname": "caguero", "type": "user", "account_id": "557058:4ded1ddf-947e-4154-bbd1-3dba24f1bdbd"}, "date": "2015-11-10T00:54:38.522898+00:00"}, "pull_request": {"type": "pullrequest", "id": 277, "links": {"self": {"href": "data/repositories/osrf/gazebo_tutorials/pullrequests/277.json"}, "html": {"href": "#!/osrf/gazebo_tutorials/pull-requests/277"}}, "title": "Wide angle camera tutorial"}}, {"update": {"description": "Redo of pull request #265.\r\n\r\n**Note**: The `wget` links are set to URL values that will exist after [this pull-request](https://bitbucket.org/osrf/gazebo/pull-requests/1941) is merged.\r\n\r\nhttp://gazebosim.org/tutorials?tut=wide_angle_camera&branch=wideangle", "title": "Wide angle camera tutorial", "destination": {"commit": {"hash": "1381e2fb3df1", "type": "commit", "links": {"self": {"href": "data/repositories/osrf/gazebo_tutorials/commit/1381e2fb3df1.json"}, "html": {"href": "#!/osrf/gazebo_tutorials/commits/1381e2fb3df1"}}}, "repository": {"links": {"self": {"href": "data/repositories/osrf/gazebo_tutorials.json"}, "html": {"href": "#!/osrf/gazebo_tutorials"}, "avatar": {"href": "data/bytebucket.org/ravatar/{9adb672c-d31a-4c2b-bae4-8d5870291649}ts=1736722"}}, "type": "repository", "name": "gazebo_tutorials", "full_name": "osrf/gazebo_tutorials", "uuid": "{9adb672c-d31a-4c2b-bae4-8d5870291649}"}, "branch": {"name": "default"}}, "reason": "", "source": {"commit": {"hash": "b1cb559a8fbe", "type": "commit", "links": {"self": {"href": "data/repositories/osrf/gazebo_tutorials/commit/b1cb559a8fbe.json"}, "html": {"href": "#!/osrf/gazebo_tutorials/commits/b1cb559a8fbe"}}}, "repository": {"links": {"self": {"href": "data/repositories/osrf/gazebo_tutorials.json"}, "html": {"href": "#!/osrf/gazebo_tutorials"}, "avatar": {"href": "data/bytebucket.org/ravatar/{9adb672c-d31a-4c2b-bae4-8d5870291649}ts=1736722"}}, "type": "repository", "name": "gazebo_tutorials", "full_name": "osrf/gazebo_tutorials", "uuid": "{9adb672c-d31a-4c2b-bae4-8d5870291649}"}, "branch": {"name": "wideangle"}}, "state": "OPEN", "author": {"display_name": "Carlos Ag\u00fcero", "uuid": "{da8a8e89-4bb0-421b-bd0e-dbbed3d4ed6a}", "links": {"self": {"href": "https://api.bitbucket.org/2.0/users/%7Bda8a8e89-4bb0-421b-bd0e-dbbed3d4ed6a%7D"}, "html": {"href": "https://bitbucket.org/%7Bda8a8e89-4bb0-421b-bd0e-dbbed3d4ed6a%7D/"}, "avatar": {"href": "data/secure.gravatar.com/avatar/692bf15758111acaddae4da15a47f9e5d=httpsavatar-management--avatars.us-west-2.prod.public.atl-paas.netinitialsCA-0.png"}}, "nickname": "caguero", "type": "user", "account_id": "557058:4ded1ddf-947e-4154-bbd1-3dba24f1bdbd"}, "date": "2015-11-10T00:54:34.306382+00:00"}, "pull_request": {"type": "pullrequest", "id": 277, "links": {"self": {"href": "data/repositories/osrf/gazebo_tutorials/pullrequests/277.json"}, "html": {"href": "#!/osrf/gazebo_tutorials/pull-requests/277"}}, "title": "Wide angle camera tutorial"}}, {"comment": {"links": {"self": {"href": "data/repositories/osrf/gazebo_tutorials/pullrequests/277/comments/11480877.json"}, "html": {"href": "#!/osrf/gazebo_tutorials/pull-requests/277/_/diff#comment-11480877"}}, "parent": {"id": 11480114, "links": {"self": {"href": "data/repositories/osrf/gazebo_tutorials/pullrequests/277/comments/11480114.json"}, "html": {"href": "#!/osrf/gazebo_tutorials/pull-requests/277/_/diff#comment-11480114"}}}, "deleted": false, "pullrequest": {"type": "pullrequest", "id": 277, "links": {"self": {"href": "data/repositories/osrf/gazebo_tutorials/pullrequests/277.json"}, "html": {"href": "#!/osrf/gazebo_tutorials/pull-requests/277"}}, "title": "Wide angle camera tutorial"}, "content": {"raw": "It was marked as [invalid](https://bitbucket.org/osrf/gazebo/issues/1763/problem-with-mouse-events-on-qt-gui), the problem was that I was trying to edit disabled fields.", "markup": "markdown", "html": "<p>It was marked as <a data-is-external-link=\"true\" href=\"https://bitbucket.org/osrf/gazebo/issues/1763/problem-with-mouse-events-on-qt-gui\" rel=\"nofollow\">invalid</a>, the problem was that I was trying to edit disabled fields.</p>", "type": "rendered"}, "created_on": "2015-11-04T20:11:09.247692+00:00", "user": {"display_name": "Louise Poubel", "uuid": "{5cfa2075-477b-4ded-bdb9-8d2479544ec4}", "links": {"self": {"href": "https://api.bitbucket.org/2.0/users/%7B5cfa2075-477b-4ded-bdb9-8d2479544ec4%7D"}, "html": {"href": "https://bitbucket.org/%7B5cfa2075-477b-4ded-bdb9-8d2479544ec4%7D/"}, "avatar": {"href": "https://avatar-management--avatars.us-west-2.prod.public.atl-paas.net/557058:6ff86fcb-b7ab-44a5-b8a6-f6d9cae8b6e8/7d903d90-c5ea-4182-b7ef-0d467e9e1c74/128"}}, "nickname": "chapulina", "type": "user", "account_id": "557058:6ff86fcb-b7ab-44a5-b8a6-f6d9cae8b6e8"}, "updated_on": "2015-11-04T20:11:09.249912+00:00", "type": "pullrequest_comment", "id": 11480877}, "pull_request": {"type": "pullrequest", "id": 277, "links": {"self": {"href": "data/repositories/osrf/gazebo_tutorials/pullrequests/277.json"}, "html": {"href": "#!/osrf/gazebo_tutorials/pull-requests/277"}}, "title": "Wide angle camera tutorial"}}, {"update": {"description": "Redo of pull request #265.\r\n\r\n**Note**: The `wget` links are set to URL values that will exist after [this pull-request](https://bitbucket.org/osrf/gazebo/pull-requests/1941) is merged.\r\n\r\nhttp://gazebosim.org/tutorials?tut=wide_angle_camera&branch=wideangle", "title": "Wide angle camera tutorial", "destination": {"commit": {"hash": "aedc2847ff6f", "type": "commit", "links": {"self": {"href": "data/repositories/osrf/gazebo_tutorials/commit/aedc2847ff6f.json"}, "html": {"href": "#!/osrf/gazebo_tutorials/commits/aedc2847ff6f"}}}, "repository": {"links": {"self": {"href": "data/repositories/osrf/gazebo_tutorials.json"}, "html": {"href": "#!/osrf/gazebo_tutorials"}, "avatar": {"href": "data/bytebucket.org/ravatar/{9adb672c-d31a-4c2b-bae4-8d5870291649}ts=1736722"}}, "type": "repository", "name": "gazebo_tutorials", "full_name": "osrf/gazebo_tutorials", "uuid": "{9adb672c-d31a-4c2b-bae4-8d5870291649}"}, "branch": {"name": "default"}}, "reason": "", "source": {"commit": {"hash": "cee871aaf408", "type": "commit", "links": {"self": {"href": "data/repositories/osrf/gazebo_tutorials/commit/cee871aaf408.json"}, "html": {"href": "#!/osrf/gazebo_tutorials/commits/cee871aaf408"}}}, "repository": {"links": {"self": {"href": "data/repositories/osrf/gazebo_tutorials.json"}, "html": {"href": "#!/osrf/gazebo_tutorials"}, "avatar": {"href": "data/bytebucket.org/ravatar/{9adb672c-d31a-4c2b-bae4-8d5870291649}ts=1736722"}}, "type": "repository", "name": "gazebo_tutorials", "full_name": "osrf/gazebo_tutorials", "uuid": "{9adb672c-d31a-4c2b-bae4-8d5870291649}"}, "branch": {"name": "wideangle"}}, "state": "OPEN", "author": {"display_name": "Nate Koenig", "uuid": "{c862cdd9-fcc8-4419-9fc7-e20db14b8fcb}", "links": {"self": {"href": "https://api.bitbucket.org/2.0/users/%7Bc862cdd9-fcc8-4419-9fc7-e20db14b8fcb%7D"}, "html": {"href": "https://bitbucket.org/%7Bc862cdd9-fcc8-4419-9fc7-e20db14b8fcb%7D/"}, "avatar": {"href": "https://avatar-management--avatars.us-west-2.prod.public.atl-paas.net/557058:095b1e12-74ed-4e20-b44f-2f0745b616e0/ca24bb11-4787-4b14-a20d-d91835e9bde2/128"}}, "nickname": "Nathan Koenig", "type": "user", "account_id": "557058:095b1e12-74ed-4e20-b44f-2f0745b616e0"}, "date": "2015-11-04T20:01:14.455061+00:00"}, "pull_request": {"type": "pullrequest", "id": 277, "links": {"self": {"href": "data/repositories/osrf/gazebo_tutorials/pullrequests/277.json"}, "html": {"href": "#!/osrf/gazebo_tutorials/pull-requests/277"}}, "title": "Wide angle camera tutorial"}}, {"update": {"description": "Redo of pull request #265.\r\n\r\n**Note**: The `wget` links are set to URL values that will exist after [this pull-request](https://bitbucket.org/osrf/gazebo/pull-requests/1941) is merged.\r\n\r\nhttp://gazebosim.org/tutorials?tut=wide_angle_camera&branch=wideangle", "title": "Wide angle camera tutorial", "destination": {"commit": {"hash": "aedc2847ff6f", "type": "commit", "links": {"self": {"href": "data/repositories/osrf/gazebo_tutorials/commit/aedc2847ff6f.json"}, "html": {"href": "#!/osrf/gazebo_tutorials/commits/aedc2847ff6f"}}}, "repository": {"links": {"self": {"href": "data/repositories/osrf/gazebo_tutorials.json"}, "html": {"href": "#!/osrf/gazebo_tutorials"}, "avatar": {"href": "data/bytebucket.org/ravatar/{9adb672c-d31a-4c2b-bae4-8d5870291649}ts=1736722"}}, "type": "repository", "name": "gazebo_tutorials", "full_name": "osrf/gazebo_tutorials", "uuid": "{9adb672c-d31a-4c2b-bae4-8d5870291649}"}, "branch": {"name": "default"}}, "reason": "", "source": {"commit": {"hash": "199e3d1f2688", "type": "commit", "links": {"self": {"href": "data/repositories/osrf/gazebo_tutorials/commit/199e3d1f2688.json"}, "html": {"href": "#!/osrf/gazebo_tutorials/commits/199e3d1f2688"}}}, "repository": {"links": {"self": {"href": "data/repositories/osrf/gazebo_tutorials.json"}, "html": {"href": "#!/osrf/gazebo_tutorials"}, "avatar": {"href": "data/bytebucket.org/ravatar/{9adb672c-d31a-4c2b-bae4-8d5870291649}ts=1736722"}}, "type": "repository", "name": "gazebo_tutorials", "full_name": "osrf/gazebo_tutorials", "uuid": "{9adb672c-d31a-4c2b-bae4-8d5870291649}"}, "branch": {"name": "wideangle"}}, "state": "OPEN", "author": {"display_name": "Nate Koenig", "uuid": "{c862cdd9-fcc8-4419-9fc7-e20db14b8fcb}", "links": {"self": {"href": "https://api.bitbucket.org/2.0/users/%7Bc862cdd9-fcc8-4419-9fc7-e20db14b8fcb%7D"}, "html": {"href": "https://bitbucket.org/%7Bc862cdd9-fcc8-4419-9fc7-e20db14b8fcb%7D/"}, "avatar": {"href": "https://avatar-management--avatars.us-west-2.prod.public.atl-paas.net/557058:095b1e12-74ed-4e20-b44f-2f0745b616e0/ca24bb11-4787-4b14-a20d-d91835e9bde2/128"}}, "nickname": "Nathan Koenig", "type": "user", "account_id": "557058:095b1e12-74ed-4e20-b44f-2f0745b616e0"}, "date": "2015-11-04T20:00:17.609841+00:00"}, "pull_request": {"type": "pullrequest", "id": 277, "links": {"self": {"href": "data/repositories/osrf/gazebo_tutorials/pullrequests/277.json"}, "html": {"href": "#!/osrf/gazebo_tutorials/pull-requests/277"}}, "title": "Wide angle camera tutorial"}}, {"update": {"description": "Redo of pull request #265.\r\n\r\n**Note**: The `wget` links are set to URL values that will exist after [this pull-request](https://bitbucket.org/osrf/gazebo/pull-requests/1941) is merged.\r\n\r\nhttp://gazebosim.org/tutorials?tut=wide_angle_camera&branch=wideangle", "title": "Wide angle camera tutorial", "destination": {"commit": {"hash": "aedc2847ff6f", "type": "commit", "links": {"self": {"href": "data/repositories/osrf/gazebo_tutorials/commit/aedc2847ff6f.json"}, "html": {"href": "#!/osrf/gazebo_tutorials/commits/aedc2847ff6f"}}}, "repository": {"links": {"self": {"href": "data/repositories/osrf/gazebo_tutorials.json"}, "html": {"href": "#!/osrf/gazebo_tutorials"}, "avatar": {"href": "data/bytebucket.org/ravatar/{9adb672c-d31a-4c2b-bae4-8d5870291649}ts=1736722"}}, "type": "repository", "name": "gazebo_tutorials", "full_name": "osrf/gazebo_tutorials", "uuid": "{9adb672c-d31a-4c2b-bae4-8d5870291649}"}, "branch": {"name": "default"}}, "reason": "", "source": {"commit": {"hash": "ec8ace95fafe", "type": "commit", "links": {"self": {"href": "data/repositories/osrf/gazebo_tutorials/commit/ec8ace95fafe.json"}, "html": {"href": "#!/osrf/gazebo_tutorials/commits/ec8ace95fafe"}}}, "repository": {"links": {"self": {"href": "data/repositories/osrf/gazebo_tutorials.json"}, "html": {"href": "#!/osrf/gazebo_tutorials"}, "avatar": {"href": "data/bytebucket.org/ravatar/{9adb672c-d31a-4c2b-bae4-8d5870291649}ts=1736722"}}, "type": "repository", "name": "gazebo_tutorials", "full_name": "osrf/gazebo_tutorials", "uuid": "{9adb672c-d31a-4c2b-bae4-8d5870291649}"}, "branch": {"name": "wideangle"}}, "state": "OPEN", "author": {"display_name": "Nate Koenig", "uuid": "{c862cdd9-fcc8-4419-9fc7-e20db14b8fcb}", "links": {"self": {"href": "https://api.bitbucket.org/2.0/users/%7Bc862cdd9-fcc8-4419-9fc7-e20db14b8fcb%7D"}, "html": {"href": "https://bitbucket.org/%7Bc862cdd9-fcc8-4419-9fc7-e20db14b8fcb%7D/"}, "avatar": {"href": "https://avatar-management--avatars.us-west-2.prod.public.atl-paas.net/557058:095b1e12-74ed-4e20-b44f-2f0745b616e0/ca24bb11-4787-4b14-a20d-d91835e9bde2/128"}}, "nickname": "Nathan Koenig", "type": "user", "account_id": "557058:095b1e12-74ed-4e20-b44f-2f0745b616e0"}, "date": "2015-11-04T20:00:00.612456+00:00"}, "pull_request": {"type": "pullrequest", "id": 277, "links": {"self": {"href": "data/repositories/osrf/gazebo_tutorials/pullrequests/277.json"}, "html": {"href": "#!/osrf/gazebo_tutorials/pull-requests/277"}}, "title": "Wide angle camera tutorial"}}, {"update": {"description": "Redo of pull request #265.\r\n\r\n**Note**: The `wget` links are set to URL values that will exist after [this pull-request](https://bitbucket.org/osrf/gazebo/pull-requests/1941) is merged.\r\n\r\nhttp://gazebosim.org/tutorials?tut=wide_angle_camera&branch=wideangle", "title": "Wide angle camera tutorial", "destination": {"commit": {"hash": "aedc2847ff6f", "type": "commit", "links": {"self": {"href": "data/repositories/osrf/gazebo_tutorials/commit/aedc2847ff6f.json"}, "html": {"href": "#!/osrf/gazebo_tutorials/commits/aedc2847ff6f"}}}, "repository": {"links": {"self": {"href": "data/repositories/osrf/gazebo_tutorials.json"}, "html": {"href": "#!/osrf/gazebo_tutorials"}, "avatar": {"href": "data/bytebucket.org/ravatar/{9adb672c-d31a-4c2b-bae4-8d5870291649}ts=1736722"}}, "type": "repository", "name": "gazebo_tutorials", "full_name": "osrf/gazebo_tutorials", "uuid": "{9adb672c-d31a-4c2b-bae4-8d5870291649}"}, "branch": {"name": "default"}}, "reason": "", "source": {"commit": {"hash": "e69b405e80df", "type": "commit", "links": {"self": {"href": "data/repositories/osrf/gazebo_tutorials/commit/e69b405e80df.json"}, "html": {"href": "#!/osrf/gazebo_tutorials/commits/e69b405e80df"}}}, "repository": {"links": {"self": {"href": "data/repositories/osrf/gazebo_tutorials.json"}, "html": {"href": "#!/osrf/gazebo_tutorials"}, "avatar": {"href": "data/bytebucket.org/ravatar/{9adb672c-d31a-4c2b-bae4-8d5870291649}ts=1736722"}}, "type": "repository", "name": "gazebo_tutorials", "full_name": "osrf/gazebo_tutorials", "uuid": "{9adb672c-d31a-4c2b-bae4-8d5870291649}"}, "branch": {"name": "wideangle"}}, "state": "OPEN", "author": {"display_name": "Nate Koenig", "uuid": "{c862cdd9-fcc8-4419-9fc7-e20db14b8fcb}", "links": {"self": {"href": "https://api.bitbucket.org/2.0/users/%7Bc862cdd9-fcc8-4419-9fc7-e20db14b8fcb%7D"}, "html": {"href": "https://bitbucket.org/%7Bc862cdd9-fcc8-4419-9fc7-e20db14b8fcb%7D/"}, "avatar": {"href": "https://avatar-management--avatars.us-west-2.prod.public.atl-paas.net/557058:095b1e12-74ed-4e20-b44f-2f0745b616e0/ca24bb11-4787-4b14-a20d-d91835e9bde2/128"}}, "nickname": "Nathan Koenig", "type": "user", "account_id": "557058:095b1e12-74ed-4e20-b44f-2f0745b616e0"}, "date": "2015-11-04T19:59:22.619980+00:00"}, "pull_request": {"type": "pullrequest", "id": 277, "links": {"self": {"href": "data/repositories/osrf/gazebo_tutorials/pullrequests/277.json"}, "html": {"href": "#!/osrf/gazebo_tutorials/pull-requests/277"}}, "title": "Wide angle camera tutorial"}}, {"update": {"description": "Redo of pull request #265.\r\n\r\n**Note**: The `wget` links are set to URL values that will exist after [this pull-request](https://bitbucket.org/osrf/gazebo/pull-requests/1941) is merged.\r\n\r\nhttp://gazebosim.org/tutorials?tut=wide_angle_camera&branch=wideangle", "title": "Wide angle camera tutorial", "destination": {"commit": {"hash": "aedc2847ff6f", "type": "commit", "links": {"self": {"href": "data/repositories/osrf/gazebo_tutorials/commit/aedc2847ff6f.json"}, "html": {"href": "#!/osrf/gazebo_tutorials/commits/aedc2847ff6f"}}}, "repository": {"links": {"self": {"href": "data/repositories/osrf/gazebo_tutorials.json"}, "html": {"href": "#!/osrf/gazebo_tutorials"}, "avatar": {"href": "data/bytebucket.org/ravatar/{9adb672c-d31a-4c2b-bae4-8d5870291649}ts=1736722"}}, "type": "repository", "name": "gazebo_tutorials", "full_name": "osrf/gazebo_tutorials", "uuid": "{9adb672c-d31a-4c2b-bae4-8d5870291649}"}, "branch": {"name": "default"}}, "reason": "", "source": {"commit": {"hash": "82559d12a22a", "type": "commit", "links": {"self": {"href": "data/repositories/osrf/gazebo_tutorials/commit/82559d12a22a.json"}, "html": {"href": "#!/osrf/gazebo_tutorials/commits/82559d12a22a"}}}, "repository": {"links": {"self": {"href": "data/repositories/osrf/gazebo_tutorials.json"}, "html": {"href": "#!/osrf/gazebo_tutorials"}, "avatar": {"href": "data/bytebucket.org/ravatar/{9adb672c-d31a-4c2b-bae4-8d5870291649}ts=1736722"}}, "type": "repository", "name": "gazebo_tutorials", "full_name": "osrf/gazebo_tutorials", "uuid": "{9adb672c-d31a-4c2b-bae4-8d5870291649}"}, "branch": {"name": "wideangle"}}, "state": "OPEN", "author": {"display_name": "Nate Koenig", "uuid": "{c862cdd9-fcc8-4419-9fc7-e20db14b8fcb}", "links": {"self": {"href": "https://api.bitbucket.org/2.0/users/%7Bc862cdd9-fcc8-4419-9fc7-e20db14b8fcb%7D"}, "html": {"href": "https://bitbucket.org/%7Bc862cdd9-fcc8-4419-9fc7-e20db14b8fcb%7D/"}, "avatar": {"href": "https://avatar-management--avatars.us-west-2.prod.public.atl-paas.net/557058:095b1e12-74ed-4e20-b44f-2f0745b616e0/ca24bb11-4787-4b14-a20d-d91835e9bde2/128"}}, "nickname": "Nathan Koenig", "type": "user", "account_id": "557058:095b1e12-74ed-4e20-b44f-2f0745b616e0"}, "date": "2015-11-04T19:58:14.525381+00:00"}, "pull_request": {"type": "pullrequest", "id": 277, "links": {"self": {"href": "data/repositories/osrf/gazebo_tutorials/pullrequests/277.json"}, "html": {"href": "#!/osrf/gazebo_tutorials/pull-requests/277"}}, "title": "Wide angle camera tutorial"}}, {"update": {"description": "Redo of pull request #265.\r\n\r\n**Note**: The `wget` links are set to URL values that will exist after [this pull-request](https://bitbucket.org/osrf/gazebo/pull-requests/1941) is merged.\r\n\r\nhttp://gazebosim.org/tutorials?tut=wide_angle_camera&branch=wideangle", "title": "Wide angle camera tutorial", "destination": {"commit": {"hash": "aedc2847ff6f", "type": "commit", "links": {"self": {"href": "data/repositories/osrf/gazebo_tutorials/commit/aedc2847ff6f.json"}, "html": {"href": "#!/osrf/gazebo_tutorials/commits/aedc2847ff6f"}}}, "repository": {"links": {"self": {"href": "data/repositories/osrf/gazebo_tutorials.json"}, "html": {"href": "#!/osrf/gazebo_tutorials"}, "avatar": {"href": "data/bytebucket.org/ravatar/{9adb672c-d31a-4c2b-bae4-8d5870291649}ts=1736722"}}, "type": "repository", "name": "gazebo_tutorials", "full_name": "osrf/gazebo_tutorials", "uuid": "{9adb672c-d31a-4c2b-bae4-8d5870291649}"}, "branch": {"name": "default"}}, "reason": "", "source": {"commit": {"hash": "a8dd52cc9ff2", "type": "commit", "links": {"self": {"href": "data/repositories/osrf/gazebo_tutorials/commit/a8dd52cc9ff2.json"}, "html": {"href": "#!/osrf/gazebo_tutorials/commits/a8dd52cc9ff2"}}}, "repository": {"links": {"self": {"href": "data/repositories/osrf/gazebo_tutorials.json"}, "html": {"href": "#!/osrf/gazebo_tutorials"}, "avatar": {"href": "data/bytebucket.org/ravatar/{9adb672c-d31a-4c2b-bae4-8d5870291649}ts=1736722"}}, "type": "repository", "name": "gazebo_tutorials", "full_name": "osrf/gazebo_tutorials", "uuid": "{9adb672c-d31a-4c2b-bae4-8d5870291649}"}, "branch": {"name": "wideangle"}}, "state": "OPEN", "author": {"display_name": "Nate Koenig", "uuid": "{c862cdd9-fcc8-4419-9fc7-e20db14b8fcb}", "links": {"self": {"href": "https://api.bitbucket.org/2.0/users/%7Bc862cdd9-fcc8-4419-9fc7-e20db14b8fcb%7D"}, "html": {"href": "https://bitbucket.org/%7Bc862cdd9-fcc8-4419-9fc7-e20db14b8fcb%7D/"}, "avatar": {"href": "https://avatar-management--avatars.us-west-2.prod.public.atl-paas.net/557058:095b1e12-74ed-4e20-b44f-2f0745b616e0/ca24bb11-4787-4b14-a20d-d91835e9bde2/128"}}, "nickname": "Nathan Koenig", "type": "user", "account_id": "557058:095b1e12-74ed-4e20-b44f-2f0745b616e0"}, "date": "2015-11-04T19:56:57.839294+00:00"}, "pull_request": {"type": "pullrequest", "id": 277, "links": {"self": {"href": "data/repositories/osrf/gazebo_tutorials/pullrequests/277.json"}, "html": {"href": "#!/osrf/gazebo_tutorials/pull-requests/277"}}, "title": "Wide angle camera tutorial"}}, {"comment": {"links": {"self": {"href": "data/repositories/osrf/gazebo_tutorials/pullrequests/277/comments/11480114.json"}, "html": {"href": "#!/osrf/gazebo_tutorials/pull-requests/277/_/diff#comment-11480114"}}, "parent": {"id": 10690080, "links": {"self": {"href": "data/repositories/osrf/gazebo_tutorials/pullrequests/277/comments/10690080.json"}, "html": {"href": "#!/osrf/gazebo_tutorials/pull-requests/277/_/diff#comment-10690080"}}}, "deleted": false, "pullrequest": {"type": "pullrequest", "id": 277, "links": {"self": {"href": "data/repositories/osrf/gazebo_tutorials/pullrequests/277.json"}, "html": {"href": "#!/osrf/gazebo_tutorials/pull-requests/277"}}, "title": "Wide angle camera tutorial"}, "content": {"raw": "Can you submit an issue to the gazebo repo?", "markup": "markdown", "html": "<p>Can you submit an issue to the gazebo repo?</p>", "type": "rendered"}, "created_on": "2015-11-04T19:51:13.719413+00:00", "user": {"display_name": "Nate Koenig", "uuid": "{c862cdd9-fcc8-4419-9fc7-e20db14b8fcb}", "links": {"self": {"href": "https://api.bitbucket.org/2.0/users/%7Bc862cdd9-fcc8-4419-9fc7-e20db14b8fcb%7D"}, "html": {"href": "https://bitbucket.org/%7Bc862cdd9-fcc8-4419-9fc7-e20db14b8fcb%7D/"}, "avatar": {"href": "https://avatar-management--avatars.us-west-2.prod.public.atl-paas.net/557058:095b1e12-74ed-4e20-b44f-2f0745b616e0/ca24bb11-4787-4b14-a20d-d91835e9bde2/128"}}, "nickname": "Nathan Koenig", "type": "user", "account_id": "557058:095b1e12-74ed-4e20-b44f-2f0745b616e0"}, "updated_on": "2015-11-04T19:51:13.722196+00:00", "type": "pullrequest_comment", "id": 11480114}, "pull_request": {"type": "pullrequest", "id": 277, "links": {"self": {"href": "data/repositories/osrf/gazebo_tutorials/pullrequests/277.json"}, "html": {"href": "#!/osrf/gazebo_tutorials/pull-requests/277"}}, "title": "Wide angle camera tutorial"}}, {"update": {"description": "Redo of pull request #265.\r\n\r\n**Note**: The `wget` links are set to URL values that will exist after [this pull-request](https://bitbucket.org/osrf/gazebo/pull-requests/1941) is merged.\r\n\r\nhttp://gazebosim.org/tutorials?tut=wide_angle_camera&branch=wideangle", "title": "Wide angle camera tutorial", "destination": {"commit": {"hash": "d97a962510d0", "type": "commit", "links": {"self": {"href": "data/repositories/osrf/gazebo_tutorials/commit/d97a962510d0.json"}, "html": {"href": "#!/osrf/gazebo_tutorials/commits/d97a962510d0"}}}, "repository": {"links": {"self": {"href": "data/repositories/osrf/gazebo_tutorials.json"}, "html": {"href": "#!/osrf/gazebo_tutorials"}, "avatar": {"href": "data/bytebucket.org/ravatar/{9adb672c-d31a-4c2b-bae4-8d5870291649}ts=1736722"}}, "type": "repository", "name": "gazebo_tutorials", "full_name": "osrf/gazebo_tutorials", "uuid": "{9adb672c-d31a-4c2b-bae4-8d5870291649}"}, "branch": {"name": "default"}}, "reason": "", "source": {"commit": {"hash": "a443cef9c2a6", "type": "commit", "links": {"self": {"href": "data/repositories/osrf/gazebo_tutorials/commit/a443cef9c2a6.json"}, "html": {"href": "#!/osrf/gazebo_tutorials/commits/a443cef9c2a6"}}}, "repository": {"links": {"self": {"href": "data/repositories/osrf/gazebo_tutorials.json"}, "html": {"href": "#!/osrf/gazebo_tutorials"}, "avatar": {"href": "data/bytebucket.org/ravatar/{9adb672c-d31a-4c2b-bae4-8d5870291649}ts=1736722"}}, "type": "repository", "name": "gazebo_tutorials", "full_name": "osrf/gazebo_tutorials", "uuid": "{9adb672c-d31a-4c2b-bae4-8d5870291649}"}, "branch": {"name": "wideangle"}}, "state": "OPEN", "author": {"display_name": "Louise Poubel", "uuid": "{5cfa2075-477b-4ded-bdb9-8d2479544ec4}", "links": {"self": {"href": "https://api.bitbucket.org/2.0/users/%7B5cfa2075-477b-4ded-bdb9-8d2479544ec4%7D"}, "html": {"href": "https://bitbucket.org/%7B5cfa2075-477b-4ded-bdb9-8d2479544ec4%7D/"}, "avatar": {"href": "https://avatar-management--avatars.us-west-2.prod.public.atl-paas.net/557058:6ff86fcb-b7ab-44a5-b8a6-f6d9cae8b6e8/7d903d90-c5ea-4182-b7ef-0d467e9e1c74/128"}}, "nickname": "chapulina", "type": "user", "account_id": "557058:6ff86fcb-b7ab-44a5-b8a6-f6d9cae8b6e8"}, "date": "2015-10-31T01:46:56.376807+00:00"}, "pull_request": {"type": "pullrequest", "id": 277, "links": {"self": {"href": "data/repositories/osrf/gazebo_tutorials/pullrequests/277.json"}, "html": {"href": "#!/osrf/gazebo_tutorials/pull-requests/277"}}, "title": "Wide angle camera tutorial"}}, {"comment": {"links": {"self": {"href": "data/repositories/osrf/gazebo_tutorials/pullrequests/277/comments/10690270.json"}, "html": {"href": "#!/osrf/gazebo_tutorials/pull-requests/277/_/diff#comment-10690270"}}, "deleted": false, "pullrequest": {"type": "pullrequest", "id": 277, "links": {"self": {"href": "data/repositories/osrf/gazebo_tutorials/pullrequests/277.json"}, "html": {"href": "#!/osrf/gazebo_tutorials/pull-requests/277"}}, "title": "Wide angle camera tutorial"}, "content": {"raw": "I committed some changes directly to this branch: 61ff8f9.\n\nThe only problem I'm having now is not being able to test the plugin example. I haven't looked at the code yet and I'm not sure how it's supposed to work, and it's currently impossible to test changing values on the GUI.", "markup": "markdown", "html": "<p>I committed some changes directly to this branch: <a href=\"#!/osrf/gazebo_tutorials/commits/61ff8f9\" rel=\"nofollow\" class=\"ap-connect-link\">61ff8f9</a>.</p>\n<p>The only problem I'm having now is not being able to test the plugin example. I haven't looked at the code yet and I'm not sure how it's supposed to work, and it's currently impossible to test changing values on the GUI.</p>", "type": "rendered"}, "created_on": "2015-10-09T22:32:00.579797+00:00", "user": {"display_name": "Louise Poubel", "uuid": "{5cfa2075-477b-4ded-bdb9-8d2479544ec4}", "links": {"self": {"href": "https://api.bitbucket.org/2.0/users/%7B5cfa2075-477b-4ded-bdb9-8d2479544ec4%7D"}, "html": {"href": "https://bitbucket.org/%7B5cfa2075-477b-4ded-bdb9-8d2479544ec4%7D/"}, "avatar": {"href": "https://avatar-management--avatars.us-west-2.prod.public.atl-paas.net/557058:6ff86fcb-b7ab-44a5-b8a6-f6d9cae8b6e8/7d903d90-c5ea-4182-b7ef-0d467e9e1c74/128"}}, "nickname": "chapulina", "type": "user", "account_id": "557058:6ff86fcb-b7ab-44a5-b8a6-f6d9cae8b6e8"}, "updated_on": "2015-10-09T22:32:00.588411+00:00", "type": "pullrequest_comment", "id": 10690270}, "pull_request": {"type": "pullrequest", "id": 277, "links": {"self": {"href": "data/repositories/osrf/gazebo_tutorials/pullrequests/277.json"}, "html": {"href": "#!/osrf/gazebo_tutorials/pull-requests/277"}}, "title": "Wide angle camera tutorial"}}, {"update": {"description": "Redo of pull request #265.\r\n\r\n**Note**: The `wget` links are set to URL values that will exist after [this pull-request](https://bitbucket.org/osrf/gazebo/pull-requests/1941) is merged.\r\n\r\nhttp://gazebosim.org/tutorials?tut=wide_angle_camera&branch=wideangle", "title": "Wide angle camera tutorial", "destination": {"commit": {"hash": "7a7739cb7e5d", "type": "commit", "links": {"self": {"href": "data/repositories/osrf/gazebo_tutorials/commit/7a7739cb7e5d.json"}, "html": {"href": "#!/osrf/gazebo_tutorials/commits/7a7739cb7e5d"}}}, "repository": {"links": {"self": {"href": "data/repositories/osrf/gazebo_tutorials.json"}, "html": {"href": "#!/osrf/gazebo_tutorials"}, "avatar": {"href": "data/bytebucket.org/ravatar/{9adb672c-d31a-4c2b-bae4-8d5870291649}ts=1736722"}}, "type": "repository", "name": "gazebo_tutorials", "full_name": "osrf/gazebo_tutorials", "uuid": "{9adb672c-d31a-4c2b-bae4-8d5870291649}"}, "branch": {"name": "default"}}, "reason": "", "source": {"commit": {"hash": "af4082170c6b", "type": "commit", "links": {"self": {"href": "data/repositories/osrf/gazebo_tutorials/commit/af4082170c6b.json"}, "html": {"href": "#!/osrf/gazebo_tutorials/commits/af4082170c6b"}}}, "repository": {"links": {"self": {"href": "data/repositories/osrf/gazebo_tutorials.json"}, "html": {"href": "#!/osrf/gazebo_tutorials"}, "avatar": {"href": "data/bytebucket.org/ravatar/{9adb672c-d31a-4c2b-bae4-8d5870291649}ts=1736722"}}, "type": "repository", "name": "gazebo_tutorials", "full_name": "osrf/gazebo_tutorials", "uuid": "{9adb672c-d31a-4c2b-bae4-8d5870291649}"}, "branch": {"name": "wideangle"}}, "state": "OPEN", "author": {"display_name": "Louise Poubel", "uuid": "{5cfa2075-477b-4ded-bdb9-8d2479544ec4}", "links": {"self": {"href": "https://api.bitbucket.org/2.0/users/%7B5cfa2075-477b-4ded-bdb9-8d2479544ec4%7D"}, "html": {"href": "https://bitbucket.org/%7B5cfa2075-477b-4ded-bdb9-8d2479544ec4%7D/"}, "avatar": {"href": "https://avatar-management--avatars.us-west-2.prod.public.atl-paas.net/557058:6ff86fcb-b7ab-44a5-b8a6-f6d9cae8b6e8/7d903d90-c5ea-4182-b7ef-0d467e9e1c74/128"}}, "nickname": "chapulina", "type": "user", "account_id": "557058:6ff86fcb-b7ab-44a5-b8a6-f6d9cae8b6e8"}, "date": "2015-10-09T22:28:51.874244+00:00"}, "pull_request": {"type": "pullrequest", "id": 277, "links": {"self": {"href": "data/repositories/osrf/gazebo_tutorials/pullrequests/277.json"}, "html": {"href": "#!/osrf/gazebo_tutorials/pull-requests/277"}}, "title": "Wide angle camera tutorial"}}, {"update": {"description": "Redo of pull request #265.\r\n\r\n**Note**: The `wget` links are set to URL values that will exist after [this pull-request](https://bitbucket.org/osrf/gazebo/pull-requests/1941) is merged.\r\n\r\nhttp://gazebosim.org/tutorials?tut=wide_angle_camera&branch=wideangle", "title": "Wide angle camera tutorial", "destination": {"commit": {"hash": "7a7739cb7e5d", "type": "commit", "links": {"self": {"href": "data/repositories/osrf/gazebo_tutorials/commit/7a7739cb7e5d.json"}, "html": {"href": "#!/osrf/gazebo_tutorials/commits/7a7739cb7e5d"}}}, "repository": {"links": {"self": {"href": "data/repositories/osrf/gazebo_tutorials.json"}, "html": {"href": "#!/osrf/gazebo_tutorials"}, "avatar": {"href": "data/bytebucket.org/ravatar/{9adb672c-d31a-4c2b-bae4-8d5870291649}ts=1736722"}}, "type": "repository", "name": "gazebo_tutorials", "full_name": "osrf/gazebo_tutorials", "uuid": "{9adb672c-d31a-4c2b-bae4-8d5870291649}"}, "branch": {"name": "default"}}, "reason": "", "source": {"commit": {"hash": "61ff8f938521", "type": "commit", "links": {"self": {"href": "data/repositories/osrf/gazebo_tutorials/commit/61ff8f938521.json"}, "html": {"href": "#!/osrf/gazebo_tutorials/commits/61ff8f938521"}}}, "repository": {"links": {"self": {"href": "data/repositories/osrf/gazebo_tutorials.json"}, "html": {"href": "#!/osrf/gazebo_tutorials"}, "avatar": {"href": "data/bytebucket.org/ravatar/{9adb672c-d31a-4c2b-bae4-8d5870291649}ts=1736722"}}, "type": "repository", "name": "gazebo_tutorials", "full_name": "osrf/gazebo_tutorials", "uuid": "{9adb672c-d31a-4c2b-bae4-8d5870291649}"}, "branch": {"name": "wideangle"}}, "state": "OPEN", "author": {"display_name": "Louise Poubel", "uuid": "{5cfa2075-477b-4ded-bdb9-8d2479544ec4}", "links": {"self": {"href": "https://api.bitbucket.org/2.0/users/%7B5cfa2075-477b-4ded-bdb9-8d2479544ec4%7D"}, "html": {"href": "https://bitbucket.org/%7B5cfa2075-477b-4ded-bdb9-8d2479544ec4%7D/"}, "avatar": {"href": "https://avatar-management--avatars.us-west-2.prod.public.atl-paas.net/557058:6ff86fcb-b7ab-44a5-b8a6-f6d9cae8b6e8/7d903d90-c5ea-4182-b7ef-0d467e9e1c74/128"}}, "nickname": "chapulina", "type": "user", "account_id": "557058:6ff86fcb-b7ab-44a5-b8a6-f6d9cae8b6e8"}, "date": "2015-10-09T22:23:03.561408+00:00"}, "pull_request": {"type": "pullrequest", "id": 277, "links": {"self": {"href": "data/repositories/osrf/gazebo_tutorials/pullrequests/277.json"}, "html": {"href": "#!/osrf/gazebo_tutorials/pull-requests/277"}}, "title": "Wide angle camera tutorial"}}, {"comment": {"links": {"self": {"href": "data/repositories/osrf/gazebo_tutorials/pullrequests/277/comments/10690080.json"}, "html": {"href": "#!/osrf/gazebo_tutorials/pull-requests/277/_/diff#comment-10690080"}}, "deleted": false, "pullrequest": {"type": "pullrequest", "id": 277, "links": {"self": {"href": "data/repositories/osrf/gazebo_tutorials/pullrequests/277.json"}, "html": {"href": "#!/osrf/gazebo_tutorials/pull-requests/277"}}, "title": "Wide angle camera tutorial"}, "content": {"raw": "I'm not sure where the problem is, but it's very hard to edit values on the GUI overlay because the mouse events go to the 3D scene behind instead.", "markup": "markdown", "html": "<p>I'm not sure where the problem is, but it's very hard to edit values on the GUI overlay because the mouse events go to the 3D scene behind instead.</p>", "type": "rendered"}, "created_on": "2015-10-09T22:17:31.542965+00:00", "user": {"display_name": "Louise Poubel", "uuid": "{5cfa2075-477b-4ded-bdb9-8d2479544ec4}", "links": {"self": {"href": "https://api.bitbucket.org/2.0/users/%7B5cfa2075-477b-4ded-bdb9-8d2479544ec4%7D"}, "html": {"href": "https://bitbucket.org/%7B5cfa2075-477b-4ded-bdb9-8d2479544ec4%7D/"}, "avatar": {"href": "https://avatar-management--avatars.us-west-2.prod.public.atl-paas.net/557058:6ff86fcb-b7ab-44a5-b8a6-f6d9cae8b6e8/7d903d90-c5ea-4182-b7ef-0d467e9e1c74/128"}}, "nickname": "chapulina", "type": "user", "account_id": "557058:6ff86fcb-b7ab-44a5-b8a6-f6d9cae8b6e8"}, "updated_on": "2015-10-09T22:17:31.547919+00:00", "type": "pullrequest_comment", "id": 10690080}, "pull_request": {"type": "pullrequest", "id": 277, "links": {"self": {"href": "data/repositories/osrf/gazebo_tutorials/pullrequests/277.json"}, "html": {"href": "#!/osrf/gazebo_tutorials/pull-requests/277"}}, "title": "Wide angle camera tutorial"}}, {"comment": {"links": {"self": {"href": "data/repositories/osrf/gazebo_tutorials/pullrequests/277/comments/10656725.json"}, "html": {"href": "#!/osrf/gazebo_tutorials/pull-requests/277/_/diff#comment-10656725"}}, "parent": {"id": 10656176, "links": {"self": {"href": "data/repositories/osrf/gazebo_tutorials/pullrequests/277/comments/10656176.json"}, "html": {"href": "#!/osrf/gazebo_tutorials/pull-requests/277/_/diff#comment-10656176"}}}, "deleted": false, "pullrequest": {"type": "pullrequest", "id": 277, "links": {"self": {"href": "data/repositories/osrf/gazebo_tutorials/pullrequests/277.json"}, "html": {"href": "#!/osrf/gazebo_tutorials/pull-requests/277"}}, "title": "Wide angle camera tutorial"}, "content": {"raw": "Sure, make changes as needed. I won't be around over the next week, so have at it.", "markup": "markdown", "html": "<p>Sure, make changes as needed. I won't be around over the next week, so have at it.</p>", "type": "rendered"}, "created_on": "2015-10-09T01:15:42.641415+00:00", "user": {"display_name": "Nate Koenig", "uuid": "{c862cdd9-fcc8-4419-9fc7-e20db14b8fcb}", "links": {"self": {"href": "https://api.bitbucket.org/2.0/users/%7Bc862cdd9-fcc8-4419-9fc7-e20db14b8fcb%7D"}, "html": {"href": "https://bitbucket.org/%7Bc862cdd9-fcc8-4419-9fc7-e20db14b8fcb%7D/"}, "avatar": {"href": "https://avatar-management--avatars.us-west-2.prod.public.atl-paas.net/557058:095b1e12-74ed-4e20-b44f-2f0745b616e0/ca24bb11-4787-4b14-a20d-d91835e9bde2/128"}}, "nickname": "Nathan Koenig", "type": "user", "account_id": "557058:095b1e12-74ed-4e20-b44f-2f0745b616e0"}, "inline": {}, "updated_on": "2015-10-09T01:15:42.644202+00:00", "type": "pullrequest_comment", "id": 10656725}, "pull_request": {"type": "pullrequest", "id": 277, "links": {"self": {"href": "data/repositories/osrf/gazebo_tutorials/pullrequests/277.json"}, "html": {"href": "#!/osrf/gazebo_tutorials/pull-requests/277"}}, "title": "Wide angle camera tutorial"}}, {"comment": {"links": {"self": {"href": "data/repositories/osrf/gazebo_tutorials/pullrequests/277/comments/10656176.json"}, "html": {"href": "#!/osrf/gazebo_tutorials/pull-requests/277/_/diff#comment-10656176"}}, "deleted": false, "pullrequest": {"type": "pullrequest", "id": 277, "links": {"self": {"href": "data/repositories/osrf/gazebo_tutorials/pullrequests/277.json"}, "html": {"href": "#!/osrf/gazebo_tutorials/pull-requests/277"}}, "title": "Wide angle camera tutorial"}, "content": {"raw": "This link shows how to use pre-made plugins. Maybe the [tutorial](http://gazebosim.org/tutorials?tut=plugins_hello_world&cat=write_plugin) on what plugins are would be better here?\n\n", "markup": "markdown", "html": "<p>This link shows how to use pre-made plugins. Maybe the <a data-is-external-link=\"true\" href=\"http://gazebosim.org/tutorials?tut=plugins_hello_world&amp;cat=write_plugin\" rel=\"nofollow\">tutorial</a> on what plugins are would be better here?</p>", "type": "rendered"}, "created_on": "2015-10-09T00:44:38.289767+00:00", "user": {"display_name": "Louise Poubel", "uuid": "{5cfa2075-477b-4ded-bdb9-8d2479544ec4}", "links": {"self": {"href": "https://api.bitbucket.org/2.0/users/%7B5cfa2075-477b-4ded-bdb9-8d2479544ec4%7D"}, "html": {"href": "https://bitbucket.org/%7B5cfa2075-477b-4ded-bdb9-8d2479544ec4%7D/"}, "avatar": {"href": "https://avatar-management--avatars.us-west-2.prod.public.atl-paas.net/557058:6ff86fcb-b7ab-44a5-b8a6-f6d9cae8b6e8/7d903d90-c5ea-4182-b7ef-0d467e9e1c74/128"}}, "nickname": "chapulina", "type": "user", "account_id": "557058:6ff86fcb-b7ab-44a5-b8a6-f6d9cae8b6e8"}, "inline": {}, "updated_on": "2015-10-09T00:44:38.297376+00:00", "type": "pullrequest_comment", "id": 10656176}, "pull_request": {"type": "pullrequest", "id": 277, "links": {"self": {"href": "data/repositories/osrf/gazebo_tutorials/pullrequests/277.json"}, "html": {"href": "#!/osrf/gazebo_tutorials/pull-requests/277"}}, "title": "Wide angle camera tutorial"}}, {"update": {"description": "Redo of pull request #265.\r\n\r\n**Note**: The `wget` links are set to URL values that will exist after [this pull-request](https://bitbucket.org/osrf/gazebo/pull-requests/1941) is merged.\r\n\r\nhttp://gazebosim.org/tutorials?tut=wide_angle_camera&branch=wideangle", "title": "Wide angle camera tutorial", "destination": {"commit": {"hash": "acc8597c61c7", "type": "commit", "links": {"self": {"href": "data/repositories/osrf/gazebo_tutorials/commit/acc8597c61c7.json"}, "html": {"href": "#!/osrf/gazebo_tutorials/commits/acc8597c61c7"}}}, "repository": {"links": {"self": {"href": "data/repositories/osrf/gazebo_tutorials.json"}, "html": {"href": "#!/osrf/gazebo_tutorials"}, "avatar": {"href": "data/bytebucket.org/ravatar/{9adb672c-d31a-4c2b-bae4-8d5870291649}ts=1736722"}}, "type": "repository", "name": "gazebo_tutorials", "full_name": "osrf/gazebo_tutorials", "uuid": "{9adb672c-d31a-4c2b-bae4-8d5870291649}"}, "branch": {"name": "default"}}, "reason": "", "source": {"commit": {"hash": "6648777b8c01", "type": "commit", "links": {"self": {"href": "data/repositories/osrf/gazebo_tutorials/commit/6648777b8c01.json"}, "html": {"href": "#!/osrf/gazebo_tutorials/commits/6648777b8c01"}}}, "repository": {"links": {"self": {"href": "data/repositories/osrf/gazebo_tutorials.json"}, "html": {"href": "#!/osrf/gazebo_tutorials"}, "avatar": {"href": "data/bytebucket.org/ravatar/{9adb672c-d31a-4c2b-bae4-8d5870291649}ts=1736722"}}, "type": "repository", "name": "gazebo_tutorials", "full_name": "osrf/gazebo_tutorials", "uuid": "{9adb672c-d31a-4c2b-bae4-8d5870291649}"}, "branch": {"name": "wideangle"}}, "state": "OPEN", "author": {"display_name": "Nate Koenig", "uuid": "{c862cdd9-fcc8-4419-9fc7-e20db14b8fcb}", "links": {"self": {"href": "https://api.bitbucket.org/2.0/users/%7Bc862cdd9-fcc8-4419-9fc7-e20db14b8fcb%7D"}, "html": {"href": "https://bitbucket.org/%7Bc862cdd9-fcc8-4419-9fc7-e20db14b8fcb%7D/"}, "avatar": {"href": "https://avatar-management--avatars.us-west-2.prod.public.atl-paas.net/557058:095b1e12-74ed-4e20-b44f-2f0745b616e0/ca24bb11-4787-4b14-a20d-d91835e9bde2/128"}}, "nickname": "Nathan Koenig", "type": "user", "account_id": "557058:095b1e12-74ed-4e20-b44f-2f0745b616e0"}, "date": "2015-10-08T15:28:15.280485+00:00"}, "pull_request": {"type": "pullrequest", "id": 277, "links": {"self": {"href": "data/repositories/osrf/gazebo_tutorials/pullrequests/277.json"}, "html": {"href": "#!/osrf/gazebo_tutorials/pull-requests/277"}}, "title": "Wide angle camera tutorial"}}, {"update": {"description": "Redo of pull request #265.\r\n\r\n**Note**: The `wget` links are set to URL values that will exist after [this pull-request](https://bitbucket.org/osrf/gazebo/pull-requests/1941) is merged.", "title": "Wide angle camera tutorial", "destination": {"commit": {"hash": "acc8597c61c7", "type": "commit", "links": {"self": {"href": "data/repositories/osrf/gazebo_tutorials/commit/acc8597c61c7.json"}, "html": {"href": "#!/osrf/gazebo_tutorials/commits/acc8597c61c7"}}}, "repository": {"links": {"self": {"href": "data/repositories/osrf/gazebo_tutorials.json"}, "html": {"href": "#!/osrf/gazebo_tutorials"}, "avatar": {"href": "data/bytebucket.org/ravatar/{9adb672c-d31a-4c2b-bae4-8d5870291649}ts=1736722"}}, "type": "repository", "name": "gazebo_tutorials", "full_name": "osrf/gazebo_tutorials", "uuid": "{9adb672c-d31a-4c2b-bae4-8d5870291649}"}, "branch": {"name": "default"}}, "reason": "", "source": {"commit": {"hash": "6648777b8c01", "type": "commit", "links": {"self": {"href": "data/repositories/osrf/gazebo_tutorials/commit/6648777b8c01.json"}, "html": {"href": "#!/osrf/gazebo_tutorials/commits/6648777b8c01"}}}, "repository": {"links": {"self": {"href": "data/repositories/osrf/gazebo_tutorials.json"}, "html": {"href": "#!/osrf/gazebo_tutorials"}, "avatar": {"href": "data/bytebucket.org/ravatar/{9adb672c-d31a-4c2b-bae4-8d5870291649}ts=1736722"}}, "type": "repository", "name": "gazebo_tutorials", "full_name": "osrf/gazebo_tutorials", "uuid": "{9adb672c-d31a-4c2b-bae4-8d5870291649}"}, "branch": {"name": "wideangle"}}, "state": "OPEN", "author": {"display_name": "Nate Koenig", "uuid": "{c862cdd9-fcc8-4419-9fc7-e20db14b8fcb}", "links": {"self": {"href": "https://api.bitbucket.org/2.0/users/%7Bc862cdd9-fcc8-4419-9fc7-e20db14b8fcb%7D"}, "html": {"href": "https://bitbucket.org/%7Bc862cdd9-fcc8-4419-9fc7-e20db14b8fcb%7D/"}, "avatar": {"href": "https://avatar-management--avatars.us-west-2.prod.public.atl-paas.net/557058:095b1e12-74ed-4e20-b44f-2f0745b616e0/ca24bb11-4787-4b14-a20d-d91835e9bde2/128"}}, "nickname": "Nathan Koenig", "type": "user", "account_id": "557058:095b1e12-74ed-4e20-b44f-2f0745b616e0"}, "date": "2015-10-08T15:27:20.794001+00:00"}, "pull_request": {"type": "pullrequest", "id": 277, "links": {"self": {"href": "data/repositories/osrf/gazebo_tutorials/pullrequests/277.json"}, "html": {"href": "#!/osrf/gazebo_tutorials/pull-requests/277"}}, "title": "Wide angle camera tutorial"}}, {"update": {"description": "Redo of pull request #265.\r\n", "title": "Wide angle camera tutorial", "destination": {"commit": {"hash": "acc8597c61c7", "type": "commit", "links": {"self": {"href": "data/repositories/osrf/gazebo_tutorials/commit/acc8597c61c7.json"}, "html": {"href": "#!/osrf/gazebo_tutorials/commits/acc8597c61c7"}}}, "repository": {"links": {"self": {"href": "data/repositories/osrf/gazebo_tutorials.json"}, "html": {"href": "#!/osrf/gazebo_tutorials"}, "avatar": {"href": "data/bytebucket.org/ravatar/{9adb672c-d31a-4c2b-bae4-8d5870291649}ts=1736722"}}, "type": "repository", "name": "gazebo_tutorials", "full_name": "osrf/gazebo_tutorials", "uuid": "{9adb672c-d31a-4c2b-bae4-8d5870291649}"}, "branch": {"name": "default"}}, "reason": "", "source": {"commit": {"hash": "6648777b8c01", "type": "commit", "links": {"self": {"href": "data/repositories/osrf/gazebo_tutorials/commit/6648777b8c01.json"}, "html": {"href": "#!/osrf/gazebo_tutorials/commits/6648777b8c01"}}}, "repository": {"links": {"self": {"href": "data/repositories/osrf/gazebo_tutorials.json"}, "html": {"href": "#!/osrf/gazebo_tutorials"}, "avatar": {"href": "data/bytebucket.org/ravatar/{9adb672c-d31a-4c2b-bae4-8d5870291649}ts=1736722"}}, "type": "repository", "name": "gazebo_tutorials", "full_name": "osrf/gazebo_tutorials", "uuid": "{9adb672c-d31a-4c2b-bae4-8d5870291649}"}, "branch": {"name": "wideangle"}}, "state": "OPEN", "author": {"display_name": "Nate Koenig", "uuid": "{c862cdd9-fcc8-4419-9fc7-e20db14b8fcb}", "links": {"self": {"href": "https://api.bitbucket.org/2.0/users/%7Bc862cdd9-fcc8-4419-9fc7-e20db14b8fcb%7D"}, "html": {"href": "https://bitbucket.org/%7Bc862cdd9-fcc8-4419-9fc7-e20db14b8fcb%7D/"}, "avatar": {"href": "https://avatar-management--avatars.us-west-2.prod.public.atl-paas.net/557058:095b1e12-74ed-4e20-b44f-2f0745b616e0/ca24bb11-4787-4b14-a20d-d91835e9bde2/128"}}, "nickname": "Nathan Koenig", "type": "user", "account_id": "557058:095b1e12-74ed-4e20-b44f-2f0745b616e0"}, "date": "2015-10-08T15:25:20.160421+00:00"}, "pull_request": {"type": "pullrequest", "id": 277, "links": {"self": {"href": "data/repositories/osrf/gazebo_tutorials/pullrequests/277.json"}, "html": {"href": "#!/osrf/gazebo_tutorials/pull-requests/277"}}, "title": "Wide angle camera tutorial"}}, {"update": {"description": "Redo of pull request #265.\r\n", "title": "Wide angle camera tutorial", "destination": {"commit": {"hash": "acc8597c61c7", "type": "commit", "links": {"self": {"href": "data/repositories/osrf/gazebo_tutorials/commit/acc8597c61c7.json"}, "html": {"href": "#!/osrf/gazebo_tutorials/commits/acc8597c61c7"}}}, "repository": {"links": {"self": {"href": "data/repositories/osrf/gazebo_tutorials.json"}, "html": {"href": "#!/osrf/gazebo_tutorials"}, "avatar": {"href": "data/bytebucket.org/ravatar/{9adb672c-d31a-4c2b-bae4-8d5870291649}ts=1736722"}}, "type": "repository", "name": "gazebo_tutorials", "full_name": "osrf/gazebo_tutorials", "uuid": "{9adb672c-d31a-4c2b-bae4-8d5870291649}"}, "branch": {"name": "default"}}, "reason": "", "source": {"commit": {"hash": "6648777b8c01", "type": "commit", "links": {"self": {"href": "data/repositories/osrf/gazebo_tutorials/commit/6648777b8c01.json"}, "html": {"href": "#!/osrf/gazebo_tutorials/commits/6648777b8c01"}}}, "repository": {"links": {"self": {"href": "data/repositories/osrf/gazebo_tutorials.json"}, "html": {"href": "#!/osrf/gazebo_tutorials"}, "avatar": {"href": "data/bytebucket.org/ravatar/{9adb672c-d31a-4c2b-bae4-8d5870291649}ts=1736722"}}, "type": "repository", "name": "gazebo_tutorials", "full_name": "osrf/gazebo_tutorials", "uuid": "{9adb672c-d31a-4c2b-bae4-8d5870291649}"}, "branch": {"name": "wideangle"}}, "state": "OPEN", "author": {"display_name": "Nate Koenig", "uuid": "{c862cdd9-fcc8-4419-9fc7-e20db14b8fcb}", "links": {"self": {"href": "https://api.bitbucket.org/2.0/users/%7Bc862cdd9-fcc8-4419-9fc7-e20db14b8fcb%7D"}, "html": {"href": "https://bitbucket.org/%7Bc862cdd9-fcc8-4419-9fc7-e20db14b8fcb%7D/"}, "avatar": {"href": "https://avatar-management--avatars.us-west-2.prod.public.atl-paas.net/557058:095b1e12-74ed-4e20-b44f-2f0745b616e0/ca24bb11-4787-4b14-a20d-d91835e9bde2/128"}}, "nickname": "Nathan Koenig", "type": "user", "account_id": "557058:095b1e12-74ed-4e20-b44f-2f0745b616e0"}, "date": "2015-10-08T15:25:20.126852+00:00"}, "pull_request": {"type": "pullrequest", "id": 277, "links": {"self": {"href": "data/repositories/osrf/gazebo_tutorials/pullrequests/277.json"}, "html": {"href": "#!/osrf/gazebo_tutorials/pull-requests/277"}}, "title": "Wide angle camera tutorial"}}]}